Swabian/TimeTagger/_TimeTagger.so
Swabian/TimeTagger/__init__.py
Swabian/TimeTagger/libTimeTagger.so
Swabian/TimeTagger/libokFrontPanel.so.1
Swabian/TimeTagger/firmware/TimeTaggerController.bit
Swabian/TimeTagger/firmware/TimeTaggerUltraController.bit
Swabian/TimeTagger/firmware/TimeTaggerXController.bit
swabian_timetagger-2.20.2.dist-info/METADATA
swabian_timetagger-2.20.2.dist-info/WHEEL
swabian_timetagger-2.20.2.dist-info/RECORD
swabian_timetagger-2.20.2.dist-info/licenses/THIRD_PARTY_LICENSES.txt
