Metadata-Version: 2.2
Name: Swabian-TimeTagger
Version: 2.20.2
Summary: Python libraries for the Swabian Instruments Time Tagger
Author-Email: Swabian Instruments GmbH <support@swabianinstruments.com>
Project-URL: Homepage, https://www.swabianinstruments.com/time-tagger/downloads/
Requires-Python: >=3.8
Requires-Dist: numpy>=1.25.0
